analysis/__init__.py
analysis/contour_analyzer.py
analysis/obstruction_calculator.py
analysis/__pycache__/contour_analyzer.cpython-311.pyc
analysis/__pycache__/obstruction_calculator.cpython-311.pyc
elevation/__init__.py
elevation/elevation_api.py
elevation/__pycache__/elevation_api.cpython-311.pyc
topography/__init__.py
topography/topography_system.py
topography/__pycache__/topography_system.cpython-311.pyc
utils/__init__.py
utils/location_parser.py
utils/__pycache__/location_parser.cpython-311.pyc
astronomy_topography_system-1.1.0.dist-info/METADATA
astronomy_topography_system-1.1.0.dist-info/WHEEL
astronomy_topography_system-1.1.0.dist-info/entry_points.txt
astronomy_topography_system-1.1.0.dist-info/top_level.txt
astronomy_topography_system-1.1.0.dist-info/RECORD
